django_github_issues-0.1.0.dist-info/DESCRIPTION.rst
django_github_issues-0.1.0.dist-info/METADATA
django_github_issues-0.1.0.dist-info/RECORD
django_github_issues-0.1.0.dist-info/WHEEL
django_github_issues-0.1.0.dist-info/metadata.json
django_github_issues-0.1.0.dist-info/top_level.txt
github_issues/__init__.py
github_issues/admin.py
github_issues/app_settings.py
github_issues/apps.py
github_issues/choices.py
github_issues/filters.py
github_issues/managers.py
github_issues/models.py
github_issues/serializers.py
github_issues/urls.py
github_issues/utils.py
github_issues/views.py
github_issues/viewsets.py
github_issues/migrations/0001_initial.py
github_issues/migrations/__init__.py
