Metadata-Version: 2.0
Name: django-github-issues
Version: 0.1.0
Summary: Django App to sync GitHub issues
Home-page: https://github.com/genomics-geek/django-github-issues
Author: Michael A. Gonzalez
Author-email: genomics.geek.04.22@gmail.com
License: MIT
Keywords: django-github-issues
Platform: UNKNOWN
Classifier: Development Status :: 3 - Alpha
Classifier: Framework :: Django
Classifier: Framework :: Django :: 1.10
Classifier: Framework :: Django :: 1.11
Classifier: Intended Audience :: Developers
Classifier: License :: OSI Approved :: BSD License
Classifier: Natural Language :: English
Classifier: Programming Language :: Python :: 2
Classifier: Programming Language :: Python :: 2.7
Classifier: Programming Language :: Python :: 3
Classifier: Programming Language :: Python :: 3.4
Classifier: Programming Language :: Python :: 3.5
Requires-Dist: djangorestframework (==3.7.7)
Requires-Dist: django-filter (==1.1.0)
Requires-Dist: django-genomix (==0.4.1)
Requires-Dist: django-user-activities (==0.3.2)
Requires-Dist: Pillow (==5.0.0)
